setup.cfg
setup.py
slimmer/__init__.py
slimmer/js_function_slimmer.py
slimmer/slimit.py
slimmer/slimmer.py
slimmer.egg-info/PKG-INFO
slimmer.egg-info/SOURCES.txt
slimmer.egg-info/dependency_links.txt
slimmer.egg-info/entry_points.txt
slimmer.egg-info/top_level.txt
slimmer.egg-info/zip-safe
slimmer/tests/__init__.py
slimmer/tests/codechunks.py
slimmer/tests/testSlimmer.py