Metadata-Version: 1.0
Name: slimmer
Version: 0.1.27
Summary: HTML,XHTML,CSS,JavaScript optimizer
Home-page: http://www.fry-it.com
Author: Peter Bengtsson
Author-email: peter@fry-it.com
License: Python
Keywords: slimmer optimizer optimiser whitespace
Platform: UNKNOWN
Classifier: Development Status :: 5 - Production/Stable
Classifier: Environment :: Other Environment
Classifier: Environment :: Web Environment
Classifier: Intended Audience :: Developers
Classifier: License :: OSI Approved :: Python Software Foundation License
Classifier: Operating System :: OS Independent
Classifier: Programming Language :: Python
Classifier: Topic :: Communications
Classifier: Topic :: Internet :: WWW/HTTP
Classifier: Topic :: Other/Nonlisted Topic
Classifier: Topic :: Software Development :: Libraries :: Python Modules
